dotsync/__init__.py
dotsync/__main__.py
dotsync/args.py
dotsync/calc_ops.py
dotsync/checks.py
dotsync/enums.py
dotsync/file_ops.py
dotsync/flists.py
dotsync/git.py
dotsync/info.py
dotsync/plugin.py
dotsync/plugins/__init__.py
dotsync/plugins/encrypt.py
dotsync/plugins/plain.py
dotsync_cli-1.0.13.dist-info/METADATA
dotsync_cli-1.0.13.dist-info/WHEEL
dotsync_cli-1.0.13.dist-info/entry_points.txt
dotsync_cli-1.0.13.dist-info/licenses/LICENSE
dotsync_cli-1.0.13.dist-info/RECORD
