Metadata-Version: 2.4
Name: dotsync-cli
Version: 1.0.13
Summary: A comprehensive solution to managing your dotfiles
Project-URL: Homepage, https://github.com/HarveyGG/dotsync
Project-URL: Documentation, https://dotsync.readthedocs.io
Project-URL: Repository, https://github.com/HarveyGG/dotsync
Project-URL: Issues, https://github.com/HarveyGG/dotsync/issues
Author-email: Harvey <harvey.wanghy@gmail.com>
License: MIT License (Non-Commercial Use Only)
License-File: LICENSE
Classifier: Development Status :: 5 - Production/Stable
Classifier: License :: Other/Proprietary License
Classifier: Operating System :: MacOS
Classifier: Operating System :: POSIX
Classifier: Programming Language :: Python :: 3
Classifier: Programming Language :: Python :: 3.8
Classifier: Programming Language :: Python :: 3.9
Classifier: Programming Language :: Python :: 3.10
Classifier: Programming Language :: Python :: 3.11
Classifier: Programming Language :: Python :: 3.12
Classifier: Programming Language :: Python :: 3.13
Classifier: Topic :: Utilities
Requires-Python: >=3.8
